processor.v
module processor(
    input wire clk,
    input wire reset,
    output reg signed [31:0] top
);

    reg [9:0] pc;
    reg [31:0] instructionMem [0:1023];
    
    reg signed [7:0] sp;
    reg signed [31:0] stack [0:255];

    reg [31:0] instruction;
    reg [4:0] opcode;
    reg signed [31:0] immediate;
    reg [9:0] memoryAddr;
    
    reg signed [31:0] dataMem [0:1023];

    reg signed [31:0] op1, op2, result;

    initial begin
        $readmemb("InstructionMem.txt",instructionMem);
        pc = 0;
        sp = -1;
    end

    always @(posedge clk or posedge reset) begin
        if(reset) begin
            pc = 0;
            sp = -1;
        end
        else begin
            instruction = instructionMem[pc];
            pc = pc + 1;

            opcode = instruction[31:27];
            immediate = {{5{instruction[26]}},instruction[26:0]};
            memoryAddr = instruction[9:0];

            case(opcode)
                5'b10000: begin // ADD
                    op2 = stack[sp];
                    sp = sp - 1;
                    op1 = stack[sp];
                    stack[sp] = op1 + op2;
                end
                5'b10001: begin // SUB
                    op2 = stack[sp];
                    sp = sp - 1;
                    op1 = stack[sp];
                    stack[sp] = op1 - op2;
                end
                5'b10010: begin // MUL
                    op2 = stack[sp];
                    sp = sp - 1;
                    op1 = stack[sp];
                    stack[sp] = op1 * op2;
                end
                5'b10011: begin // DIV
                    op2 = stack[sp];
                    sp = sp - 1;
                    op1 = stack[sp];
                    stack[sp] = op1 / op2;
                end
                5'b10100: begin // MOD
                    op2 = stack[sp];
                    sp = sp - 1;
                    op1 = stack[sp];
                    stack[sp] = op1 % op2;
                end
                5'b10101: begin // CMP
                    op2 = stack[sp];
                    sp = sp - 1;
                    op1 = stack[sp];
                    if(op1 == op2) stack[sp] = 0;
                    else if(op1 > op2) stack[sp] = 1;
                    else stack[sp] = -1;
                end
                5'b10110: begin // AND
                    op2 = stack[sp];
                    sp = sp - 1;
                    op1 = stack[sp];
                    stack[sp] = op1 & op2;
                end
                5'b10111: begin // OR
                    op2 = stack[sp];
                    sp = sp - 1;
                    op1 = stack[sp];
                    stack[sp] = op1 | op2;
                end
                5'b11000: begin // NOT
                    op1 = stack[sp];
                    stack[sp] = ~op1;
                end
                5'b11001: begin // LSL
                    op1 = stack[sp];
                    stack[sp] = op1 << 1;
                end
                5'b11010: begin // LSR
                    op1 = stack[sp];
                    stack[sp] = op1 >> 1;
                end
                5'b11011: begin // ASR
                    op1 = stack[sp];
                    stack[sp] = op1 >>> 1;
                end
                5'b01000: begin // PUSH imm
                    sp = sp + 1;
                    stack[sp] = immediate;
                end
                5'b01001: begin // PUSHM [addr]
                    sp = sp + 1;
                    stack[sp] = dataMem[memoryAddr];
                end
                5'b01010: begin // POP
                    sp = sp - 1;
                end
                5'b01011: begin // POPM [addr]
                    dataMem[memoryAddr] = stack[sp];
                    sp = sp - 1;
                end
                5'b01100: begin // DUP
                    sp = sp + 1;
                    stack[sp] = stack[sp - 1];
                end
                5'b00100: begin // JMP [addr]
                    pc = memoryAddr;
                end
                5'b00101: begin // JZ [addr]
                    if(stack[sp] == 0) pc = memoryAddr;
                    sp = sp - 1;
                end
                5'b00110: begin // JNZ [addr]
                    if(stack[sp] != 0) pc = memoryAddr;
                    sp = sp - 1;
                end
                5'b00000: begin // LOAD [addr]
                    stack[sp] = dataMem[memoryAddr];
                end
                5'b00001: begin // STORE [addr]
                    dataMem[memoryAddr] = stack[sp];
                end
                default: begin
                end
            endcase

            top = (sp >= 0) ? stack[sp] : -1;

        end
    end

endmodule

processor_tb.v
module processor_tb;
    reg clk, reset;
    output reg signed [31:0] top;

    processor uut(
        .clk(clk),
        .reset(reset),
        .top(top)
    );

    always #5 clk = ~clk;

    initial begin
        $dumpfile("processor_tb.vcd");
        $dumpvars(0, processor_tb);

        clk = 0;
        reset = 1; #10;
        reset = 0;

        #2000;
        $finish;
    end

    // initial begin
    //     $monitor("Time: %0t | Top of Stack %d", $time, top);
    // end

    initial begin
    forever begin
        #10; // Print every 10 time units
        $display("Time=%0t | Top of Stack=%d", $time, top);
    end
end

endmodule

processor_tb.vcd
$date
	Sat Feb 15 17:01:41 2025
$end
$version
	Icarus Verilog
$end
$timescale
	1s
$end
$scope module processor_tb $end
$var wire 32 ! top [31:0] $end
$var reg 1 " clk $end
$var reg 1 # reset $end
$scope module uut $end
$var wire 1 " clk $end
$var wire 1 # reset $end
$var reg 32 $ immediate [31:0] $end
$var reg 32 % instruction [31:0] $end
$var reg 10 & memoryAddr [9:0] $end
$var reg 32 ' op1 [31:0] $end
$var reg 32 ( op2 [31:0] $end
$var reg 5 ) opcode [4:0] $end
$var reg 10 * pc [9:0] $end
$var reg 8 + sp [7:0] $end
$var reg 32 , top [31:0] $end
$upscope $end
$upscope $end
$enddefinitions $end
$comment Show the parameter values. $end
$dumpall
$end
#0
$dumpvars
bx ,
b11111111 +
b0 *
bx )
bx (
bx '
bx &
bx %
bx $
1#
0"
bx !
$end
#5
1"
#10
0"
0#
#15
b1011 !
b1011 ,
b0 +
b1011 &
b1011 $
b1000 )
b1 *
b1000000000000000000000000001011 %
1"
#20
0"
#25
b1 &
b1 $
b1 )
b10 *
b1000000000000000000000000001 %
1"
#30
0"
#35
b1 +
b0 &
b0 $
b1100 )
b11 *
b1100000000000000000000000000000 %
1"
#40
0"
#45
b1 !
b1 ,
b10 +
b1 &
b1 $
b1000 )
b100 *
b1000000000000000000000000000001 %
1"
#50
0"
#55
b1010 !
b1010 ,
b1011 '
b1 +
b1 (
b0 &
b0 $
b10001 )
b101 *
b10001000000000000000000000000000 %
1"
#60
0"
#65
b10 &
b10 $
b1 )
b110 *
b1000000000000000000000000010 %
1"
#70
0"
#75
b1 !
b1 ,
b10 +
b1 &
b1 $
b1000 )
b111 *
b1000000000000000000000000000001 %
1"
#80
0"
#85
b1010 '
b1 +
b0 &
b0 $
b10101 )
b1000 *
b10101000000000000000000000000000 %
1"
#90
0"
#95
b1011 !
b1011 ,
b0 +
b10001 &
b10001 $
b101 )
b1001 *
b101000000000000000000000010001 %
1"
#100
0"
#105
b1010 !
b1010 ,
b1 +
b10 &
b10 $
b1001 )
b1010 *
b1001000000000000000000000000010 %
1"
#110
0"
#115
b1 !
b1 ,
b1011 '
b0 +
b1010 (
b0 &
b0 $
b10100 )
b1011 *
b10100000000000000000000000000000 %
1"
#120
0"
#125
b11111111111111111111111111111111 !
b11111111111111111111111111111111 ,
b11111111 +
b1111 &
b1111 $
b101 )
b1100 *
b101000000000000000000000001111 %
1"
#130
0"
#135
b1011 !
b1011 ,
b0 +
b1 &
b1 $
b1001 )
b1101 *
b1001000000000000000000000000001 %
1"
#140
0"
#145
b1010 !
b1010 ,
b1 +
b10 &
b10 $
b1110 *
b1001000000000000000000000000010 %
1"
#150
0"
#155
b11 &
b11 $
b100 )
b11 *
b100000000000000000000000000011 %
1"
#160
0"
#165
b1 !
b1 ,
b10 +
b1 &
b1 $
b1000 )
b100 *
b1000000000000000000000000000001 %
1"
#170
0"
#175
b1001 !
b1001 ,
b1010 '
b1 +
b1 (
b0 &
b0 $
b10001 )
b101 *
b10001000000000000000000000000000 %
1"
#180
0"
#185
b10 &
b10 $
b1 )
b110 *
b1000000000000000000000000010 %
1"
#190
0"
#195
b1 !
b1 ,
b10 +
b1 &
b1 $
b1000 )
b111 *
b1000000000000000000000000000001 %
1"
#200
0"
#205
b1001 '
b1 +
b0 &
b0 $
b10101 )
b1000 *
b10101000000000000000000000000000 %
1"
#210
0"
#215
b1011 !
b1011 ,
b0 +
b10001 &
b10001 $
b101 )
b1001 *
b101000000000000000000000010001 %
1"
#220
0"
#225
b1001 !
b1001 ,
b1 +
b10 &
b10 $
b1001 )
b1010 *
b1001000000000000000000000000010 %
1"
#230
0"
#235
b10 !
b10 ,
b1011 '
b0 +
b1001 (
b0 &
b0 $
b10100 )
b1011 *
b10100000000000000000000000000000 %
1"
#240
0"
#245
b11111111111111111111111111111111 !
b11111111111111111111111111111111 ,
b11111111 +
b1111 &
b1111 $
b101 )
b1100 *
b101000000000000000000000001111 %
1"
#250
0"
#255
b1011 !
b1011 ,
b0 +
b1 &
b1 $
b1001 )
b1101 *
b1001000000000000000000000000001 %
1"
#260
0"
#265
b1001 !
b1001 ,
b1 +
b10 &
b10 $
b1110 *
b1001000000000000000000000000010 %
1"
#270
0"
#275
b11 &
b11 $
b100 )
b11 *
b100000000000000000000000000011 %
1"
#280
0"
#285
b1 !
b1 ,
b10 +
b1 &
b1 $
b1000 )
b100 *
b1000000000000000000000000000001 %
1"
#290
0"
#295
b1000 !
b1000 ,
b1001 '
b1 +
b1 (
b0 &
b0 $
b10001 )
b101 *
b10001000000000000000000000000000 %
1"
#300
0"
#305
b10 &
b10 $
b1 )
b110 *
b1000000000000000000000000010 %
1"
#310
0"
#315
b1 !
b1 ,
b10 +
b1 &
b1 $
b1000 )
b111 *
b1000000000000000000000000000001 %
1"
#320
0"
#325
b1000 '
b1 +
b0 &
b0 $
b10101 )
b1000 *
b10101000000000000000000000000000 %
1"
#330
0"
#335
b1011 !
b1011 ,
b0 +
b10001 &
b10001 $
b101 )
b1001 *
b101000000000000000000000010001 %
1"
#340
0"
#345
b1000 !
b1000 ,
b1 +
b10 &
b10 $
b1001 )
b1010 *
b1001000000000000000000000000010 %
1"
#350
0"
#355
b11 !
b11 ,
b1011 '
b0 +
b1000 (
b0 &
b0 $
b10100 )
b1011 *
b10100000000000000000000000000000 %
1"
#360
0"
#365
b11111111111111111111111111111111 !
b11111111111111111111111111111111 ,
b11111111 +
b1111 &
b1111 $
b101 )
b1100 *
b101000000000000000000000001111 %
1"
#370
0"
#375
b1011 !
b1011 ,
b0 +
b1 &
b1 $
b1001 )
b1101 *
b1001000000000000000000000000001 %
1"
#380
0"
#385
b1000 !
b1000 ,
b1 +
b10 &
b10 $
b1110 *
b1001000000000000000000000000010 %
1"
#390
0"
#395
b11 &
b11 $
b100 )
b11 *
b100000000000000000000000000011 %
1"
#400
0"
#405
b1 !
b1 ,
b10 +
b1 &
b1 $
b1000 )
b100 *
b1000000000000000000000000000001 %
1"
#410
0"
#415
b111 !
b111 ,
b1000 '
b1 +
b1 (
b0 &
b0 $
b10001 )
b101 *
b10001000000000000000000000000000 %
1"
#420
0"
#425
b10 &
b10 $
b1 )
b110 *
b1000000000000000000000000010 %
1"
#430
0"
#435
b1 !
b1 ,
b10 +
b1 &
b1 $
b1000 )
b111 *
b1000000000000000000000000000001 %
1"
#440
0"
#445
b111 '
b1 +
b0 &
b0 $
b10101 )
b1000 *
b10101000000000000000000000000000 %
1"
#450
0"
#455
b1011 !
b1011 ,
b0 +
b10001 &
b10001 $
b101 )
b1001 *
b101000000000000000000000010001 %
1"
#460
0"
#465
b111 !
b111 ,
b1 +
b10 &
b10 $
b1001 )
b1010 *
b1001000000000000000000000000010 %
1"
#470
0"
#475
b100 !
b100 ,
b1011 '
b0 +
b111 (
b0 &
b0 $
b10100 )
b1011 *
b10100000000000000000000000000000 %
1"
#480
0"
#485
b11111111111111111111111111111111 !
b11111111111111111111111111111111 ,
b11111111 +
b1111 &
b1111 $
b101 )
b1100 *
b101000000000000000000000001111 %
1"
#490
0"
#495
b1011 !
b1011 ,
b0 +
b1 &
b1 $
b1001 )
b1101 *
b1001000000000000000000000000001 %
1"
#500
0"
#505
b111 !
b111 ,
b1 +
b10 &
b10 $
b1110 *
b1001000000000000000000000000010 %
1"
#510
0"
#515
b11 &
b11 $
b100 )
b11 *
b100000000000000000000000000011 %
1"
#520
0"
#525
b1 !
b1 ,
b10 +
b1 &
b1 $
b1000 )
b100 *
b1000000000000000000000000000001 %
1"
#530
0"
#535
b110 !
b110 ,
b111 '
b1 +
b1 (
b0 &
b0 $
b10001 )
b101 *
b10001000000000000000000000000000 %
1"
#540
0"
#545
b10 &
b10 $
b1 )
b110 *
b1000000000000000000000000010 %
1"
#550
0"
#555
b1 !
b1 ,
b10 +
b1 &
b1 $
b1000 )
b111 *
b1000000000000000000000000000001 %
1"
#560
0"
#565
b110 '
b1 +
b0 &
b0 $
b10101 )
b1000 *
b10101000000000000000000000000000 %
1"
#570
0"
#575
b1011 !
b1011 ,
b0 +
b10001 &
b10001 $
b101 )
b1001 *
b101000000000000000000000010001 %
1"
#580
0"
#585
b110 !
b110 ,
b1 +
b10 &
b10 $
b1001 )
b1010 *
b1001000000000000000000000000010 %
1"
#590
0"
#595
b101 !
b101 ,
b1011 '
b0 +
b110 (
b0 &
b0 $
b10100 )
b1011 *
b10100000000000000000000000000000 %
1"
#600
0"
#605
b11111111111111111111111111111111 !
b11111111111111111111111111111111 ,
b11111111 +
b1111 &
b1111 $
b101 )
b1100 *
b101000000000000000000000001111 %
1"
#610
0"
#615
b1011 !
b1011 ,
b0 +
b1 &
b1 $
b1001 )
b1101 *
b1001000000000000000000000000001 %
1"
#620
0"
#625
b110 !
b110 ,
b1 +
b10 &
b10 $
b1110 *
b1001000000000000000000000000010 %
1"
#630
0"
#635
b11 &
b11 $
b100 )
b11 *
b100000000000000000000000000011 %
1"
#640
0"
#645
b1 !
b1 ,
b10 +
b1 &
b1 $
b1000 )
b100 *
b1000000000000000000000000000001 %
1"
#650
0"
#655
b101 !
b101 ,
b110 '
b1 +
b1 (
b0 &
b0 $
b10001 )
b101 *
b10001000000000000000000000000000 %
1"
#660
0"
#665
b10 &
b10 $
b1 )
b110 *
b1000000000000000000000000010 %
1"
#670
0"
#675
b1 !
b1 ,
b10 +
b1 &
b1 $
b1000 )
b111 *
b1000000000000000000000000000001 %
1"
#680
0"
#685
b101 '
b1 +
b0 &
b0 $
b10101 )
b1000 *
b10101000000000000000000000000000 %
1"
#690
0"
#695
b1011 !
b1011 ,
b0 +
b10001 &
b10001 $
b101 )
b1001 *
b101000000000000000000000010001 %
1"
#700
0"
#705
b101 !
b101 ,
b1 +
b10 &
b10 $
b1001 )
b1010 *
b1001000000000000000000000000010 %
1"
#710
0"
#715
b1 !
b1 ,
b1011 '
b0 +
b101 (
b0 &
b0 $
b10100 )
b1011 *
b10100000000000000000000000000000 %
1"
#720
0"
#725
b11111111111111111111111111111111 !
b11111111111111111111111111111111 ,
b11111111 +
b1111 &
b1111 $
b101 )
b1100 *
b101000000000000000000000001111 %
1"
#730
0"
#735
b1011 !
b1011 ,
b0 +
b1 &
b1 $
b1001 )
b1101 *
b1001000000000000000000000000001 %
1"
#740
0"
#745
b101 !
b101 ,
b1 +
b10 &
b10 $
b1110 *
b1001000000000000000000000000010 %
1"
#750
0"
#755
b11 &
b11 $
b100 )
b11 *
b100000000000000000000000000011 %
1"
#760
0"
#765
b1 !
b1 ,
b10 +
b1 &
b1 $
b1000 )
b100 *
b1000000000000000000000000000001 %
1"
#770
0"
#775
b100 !
b100 ,
b101 '
b1 +
b1 (
b0 &
b0 $
b10001 )
b101 *
b10001000000000000000000000000000 %
1"
#780
0"
#785
b10 &
b10 $
b1 )
b110 *
b1000000000000000000000000010 %
1"
#790
0"
#795
b1 !
b1 ,
b10 +
b1 &
b1 $
b1000 )
b111 *
b1000000000000000000000000000001 %
1"
#800
0"
#805
b100 '
b1 +
b0 &
b0 $
b10101 )
b1000 *
b10101000000000000000000000000000 %
1"
#810
0"
#815
b1011 !
b1011 ,
b0 +
b10001 &
b10001 $
b101 )
b1001 *
b101000000000000000000000010001 %
1"
#820
0"
#825
b100 !
b100 ,
b1 +
b10 &
b10 $
b1001 )
b1010 *
b1001000000000000000000000000010 %
1"
#830
0"
#835
b11 !
b11 ,
b1011 '
b0 +
b100 (
b0 &
b0 $
b10100 )
b1011 *
b10100000000000000000000000000000 %
1"
#840
0"
#845
b11111111111111111111111111111111 !
b11111111111111111111111111111111 ,
b11111111 +
b1111 &
b1111 $
b101 )
b1100 *
b101000000000000000000000001111 %
1"
#850
0"
#855
b1011 !
b1011 ,
b0 +
b1 &
b1 $
b1001 )
b1101 *
b1001000000000000000000000000001 %
1"
#860
0"
#865
b100 !
b100 ,
b1 +
b10 &
b10 $
b1110 *
b1001000000000000000000000000010 %
1"
#870
0"
#875
b11 &
b11 $
b100 )
b11 *
b100000000000000000000000000011 %
1"
#880
0"
#885
b1 !
b1 ,
b10 +
b1 &
b1 $
b1000 )
b100 *
b1000000000000000000000000000001 %
1"
#890
0"
#895
b11 !
b11 ,
b100 '
b1 +
b1 (
b0 &
b0 $
b10001 )
b101 *
b10001000000000000000000000000000 %
1"
#900
0"
#905
b10 &
b10 $
b1 )
b110 *
b1000000000000000000000000010 %
1"
#910
0"
#915
b1 !
b1 ,
b10 +
b1 &
b1 $
b1000 )
b111 *
b1000000000000000000000000000001 %
1"
#920
0"
#925
b11 '
b1 +
b0 &
b0 $
b10101 )
b1000 *
b10101000000000000000000000000000 %
1"
#930
0"
#935
b1011 !
b1011 ,
b0 +
b10001 &
b10001 $
b101 )
b1001 *
b101000000000000000000000010001 %
1"
#940
0"
#945
b11 !
b11 ,
b1 +
b10 &
b10 $
b1001 )
b1010 *
b1001000000000000000000000000010 %
1"
#950
0"
#955
b10 !
b10 ,
b1011 '
b0 +
b11 (
b0 &
b0 $
b10100 )
b1011 *
b10100000000000000000000000000000 %
1"
#960
0"
#965
b11111111111111111111111111111111 !
b11111111111111111111111111111111 ,
b11111111 +
b1111 &
b1111 $
b101 )
b1100 *
b101000000000000000000000001111 %
1"
#970
0"
#975
b1011 !
b1011 ,
b0 +
b1 &
b1 $
b1001 )
b1101 *
b1001000000000000000000000000001 %
1"
#980
0"
#985
b11 !
b11 ,
b1 +
b10 &
b10 $
b1110 *
b1001000000000000000000000000010 %
1"
#990
0"
#995
b11 &
b11 $
b100 )
b11 *
b100000000000000000000000000011 %
1"
#1000
0"
#1005
b1 !
b1 ,
b10 +
b1 &
b1 $
b1000 )
b100 *
b1000000000000000000000000000001 %
1"
#1010
0"
#1015
b10 !
b10 ,
b11 '
b1 +
b1 (
b0 &
b0 $
b10001 )
b101 *
b10001000000000000000000000000000 %
1"
#1020
0"
#1025
b10 &
b10 $
b1 )
b110 *
b1000000000000000000000000010 %
1"
#1030
0"
#1035
b1 !
b1 ,
b10 +
b1 &
b1 $
b1000 )
b111 *
b1000000000000000000000000000001 %
1"
#1040
0"
#1045
b10 '
b1 +
b0 &
b0 $
b10101 )
b1000 *
b10101000000000000000000000000000 %
1"
#1050
0"
#1055
b1011 !
b1011 ,
b0 +
b10001 &
b10001 $
b101 )
b1001 *
b101000000000000000000000010001 %
1"
#1060
0"
#1065
b10 !
b10 ,
b1 +
b10 &
b10 $
b1001 )
b1010 *
b1001000000000000000000000000010 %
1"
#1070
0"
#1075
b1 !
b1 ,
b1011 '
b0 +
b10 (
b0 &
b0 $
b10100 )
b1011 *
b10100000000000000000000000000000 %
1"
#1080
0"
#1085
b11111111111111111111111111111111 !
b11111111111111111111111111111111 ,
b11111111 +
b1111 &
b1111 $
b101 )
b1100 *
b101000000000000000000000001111 %
1"
#1090
0"
#1095
b1011 !
b1011 ,
b0 +
b1 &
b1 $
b1001 )
b1101 *
b1001000000000000000000000000001 %
1"
#1100
0"
#1105
b10 !
b10 ,
b1 +
b10 &
b10 $
b1110 *
b1001000000000000000000000000010 %
1"
#1110
0"
#1115
b11 &
b11 $
b100 )
b11 *
b100000000000000000000000000011 %
1"
#1120
0"
#1125
b1 !
b1 ,
b10 +
b1 &
b1 $
b1000 )
b100 *
b1000000000000000000000000000001 %
1"
#1130
0"
#1135
b10 '
b1 +
b1 (
b0 &
b0 $
b10001 )
b101 *
b10001000000000000000000000000000 %
1"
#1140
0"
#1145
b10 &
b10 $
b1 )
b110 *
b1000000000000000000000000010 %
1"
#1150
0"
#1155
b10 +
b1 &
b1 $
b1000 )
b111 *
b1000000000000000000000000000001 %
1"
#1160
0"
#1165
b0 !
b0 ,
b1 '
b1 +
b0 &
b0 $
b10101 )
b1000 *
b10101000000000000000000000000000 %
1"
#1170
0"
#1175
b1011 !
b1011 ,
b0 +
b10001 &
b10001 $
b101 )
b10001 *
b101000000000000000000000010001 %
1"
#1180
0"
#1185
b1 !
b1 ,
b1 +
b1 &
b1 $
b1000 )
b10010 *
b1000000000000000000000000000001 %
1"
#1190
0"
#1195
b10 +
b0 &
b0 $
b1100 )
b10011 *
b1100000000000000000000000000000 %
1"
#1200
0"
#1205
bx &
bx $
bx )
b10100 *
bx %
1"
#1210
0"
#1215
b10101 *
1"
#1220
0"
#1225
b10110 *
1"
#1230
0"
#1235
b10111 *
1"
#1240
0"
#1245
b11000 *
1"
#1250
0"
#1255
b11001 *
1"
#1260
0"
#1265
b11010 *
1"
#1270
0"
#1275
b11011 *
1"
#1280
0"
#1285
b11100 *
1"
#1290
0"
#1295
b11101 *
1"
#1300
0"
#1305
b11110 *
1"
#1310
0"
#1315
b11111 *
1"
#1320
0"
#1325
b100000 *
1"
#1330
0"
#1335
b100001 *
1"
#1340
0"
#1345
b100010 *
1"
#1350
0"
#1355
b100011 *
1"
#1360
0"
#1365
b100100 *
1"
#1370
0"
#1375
b100101 *
1"
#1380
0"
#1385
b100110 *
1"
#1390
0"
#1395
b100111 *
1"
#1400
0"
#1405
b101000 *
1"
#1410
0"
#1415
b101001 *
1"
#1420
0"
#1425
b101010 *
1"
#1430
0"
#1435
b101011 *
1"
#1440
0"
#1445
b101100 *
1"
#1450
0"
#1455
b101101 *
1"
#1460
0"
#1465
b101110 *
1"
#1470
0"
#1475
b101111 *
1"
#1480
0"
#1485
b110000 *
1"
#1490
0"
#1495
b110001 *
1"
#1500
0"
#1505
b110010 *
1"
#1510
0"
#1515
b110011 *
1"
#1520
0"
#1525
b110100 *
1"
#1530
0"
#1535
b110101 *
1"
#1540
0"
#1545
b110110 *
1"
#1550
0"
#1555
b110111 *
1"
#1560
0"
#1565
b111000 *
1"
#1570
0"
#1575
b111001 *
1"
#1580
0"
#1585
b111010 *
1"
#1590
0"
#1595
b111011 *
1"
#1600
0"
#1605
b111100 *
1"
#1610
0"
#1615
b111101 *
1"
#1620
0"
#1625
b111110 *
1"
#1630
0"
#1635
b111111 *
1"
#1640
0"
#1645
b1000000 *
1"
#1650
0"
#1655
b1000001 *
1"
#1660
0"
#1665
b1000010 *
1"
#1670
0"
#1675
b1000011 *
1"
#1680
0"
#1685
b1000100 *
1"
#1690
0"
#1695
b1000101 *
1"
#1700
0"
#1705
b1000110 *
1"
#1710
0"
#1715
b1000111 *
1"
#1720
0"
#1725
b1001000 *
1"
#1730
0"
#1735
b1001001 *
1"
#1740
0"
#1745
b1001010 *
1"
#1750
0"
#1755
b1001011 *
1"
#1760
0"
#1765
b1001100 *
1"
#1770
0"
#1775
b1001101 *
1"
#1780
0"
#1785
b1001110 *
1"
#1790
0"
#1795
b1001111 *
1"
#1800
0"
#1805
b1010000 *
1"
#1810
0"
#1815
b1010001 *
1"
#1820
0"
#1825
b1010010 *
1"
#1830
0"
#1835
b1010011 *
1"
#1840
0"
#1845
b1010100 *
1"
#1850
0"
#1855
b1010101 *
1"
#1860
0"
#1865
b1010110 *
1"
#1870
0"
#1875
b1010111 *
1"
#1880
0"
#1885
b1011000 *
1"
#1890
0"
#1895
b1011001 *
1"
#1900
0"
#1905
b1011010 *
1"
#1910
0"
#1915
b1011011 *
1"
#1920
0"
#1925
b1011100 *
1"
#1930
0"
#1935
b1011101 *
1"
#1940
0"
#1945
b1011110 *
1"
#1950
0"
#1955
b1011111 *
1"
#1960
0"
#1965
b1100000 *
1"
#1970
0"
#1975
b1100001 *
1"
#1980
0"
#1985
b1100010 *
1"
#1990
0"
#1995
b1100011 *
1"
#2000
0"
#2005
b1100100 *
1"
